hammad/__init__.py
hammad/database.py
hammad/instruct.py
hammad/module.py
hammad/vector_database.py
hammad/ml/__init__.py
hammad/ml/cross_encoder.py
hammad/ml/loss.py
hammad/ml/semantic_search.py
hammad/ml/sentence_embedder.py
hammad/ml/sentence_similarity.py
hammad/modules/__init__.py
hammad/modules/inputs.py
hammad/modules/messages.py
hammad/modules/status.py
hammad/modules/verifiers.py
hammad-1.0.0.dist-info/METADATA
hammad-1.0.0.dist-info/WHEEL
hammad-1.0.0.dist-info/top_level.txt
hammad-1.0.0.dist-info/RECORD
