Metadata-Version: 2.1
Name: hammad
Version: 1.0.0
Summary: Hammad's Accelarated Micro Modules for Application Development (Hammad's Python Library)
Author: Hammad Saeed
Author-email: hammad@supportvectors.com
Classifier: Programming Language :: Python :: 3
Classifier: License :: OSI Approved :: MIT License
Classifier: Operating System :: OS Independent
Requires-Python: >3.10
Requires-Dist: aiohttp
Requires-Dist: aiosignal
Requires-Dist: annotated-types
Requires-Dist: annoy
Requires-Dist: anyio
Requires-Dist: attrs
Requires-Dist: certifi
Requires-Dist: charset-normalizer
Requires-Dist: click
Requires-Dist: colorama
Requires-Dist: distro
Requires-Dist: docstring-parser
Requires-Dist: filelock
Requires-Dist: frozenlist
Requires-Dist: fsspec
Requires-Dist: h11
Requires-Dist: httpcore
Requires-Dist: httpx
Requires-Dist: huggingface-hub
Requires-Dist: idna
Requires-Dist: instructor
Requires-Dist: Jinja2
Requires-Dist: joblib
Requires-Dist: markdown-it-py
Requires-Dist: MarkupSafe
Requires-Dist: mdurl
Requires-Dist: mpmath
Requires-Dist: multidict
Requires-Dist: networkx
Requires-Dist: numpy
Requires-Dist: openai
Requires-Dist: packaging
Requires-Dist: pandas
Requires-Dist: pillow
Requires-Dist: prompt-toolkit
Requires-Dist: pydantic
Requires-Dist: pydantic-core
Requires-Dist: Pygments
Requires-Dist: python-dateutil
Requires-Dist: pytz
Requires-Dist: PyYAML
Requires-Dist: regex
Requires-Dist: requests
Requires-Dist: rich
Requires-Dist: safetensors
Requires-Dist: scikit-learn
Requires-Dist: scipy
Requires-Dist: sentence-transformers
Requires-Dist: setuptools
Requires-Dist: six
Requires-Dist: sniffio
Requires-Dist: sympy
Requires-Dist: tenacity
Requires-Dist: threadpoolctl
Requires-Dist: tokenizers
Requires-Dist: torch
Requires-Dist: tqdm
Requires-Dist: transformers
Requires-Dist: typer
Requires-Dist: typing-extensions
Requires-Dist: tzdata
Requires-Dist: urllib3
Requires-Dist: wcwidth
Requires-Dist: wheel
Requires-Dist: Whoosh
Requires-Dist: yarl
